autofixture/__init__.py
autofixture/autofixtures.py
autofixture/base.py
autofixture/compat.py
autofixture/constraints.py
autofixture/fields.py
autofixture/generators.py
autofixture/models.py
autofixture/placeholder.py
autofixture/signals.py
autofixture/values.py
autofixture/management/__init__.py
autofixture/management/commands/__init__.py
autofixture/management/commands/loadtestdata.py
django_autofixture_squad-0.12.6.dist-info/AUTHORS.txt
django_autofixture_squad-0.12.6.dist-info/LICENSE.txt
django_autofixture_squad-0.12.6.dist-info/METADATA
django_autofixture_squad-0.12.6.dist-info/WHEEL
django_autofixture_squad-0.12.6.dist-info/top_level.txt
django_autofixture_squad-0.12.6.dist-info/RECORD
